{"code":"200","updateTime":"2023-08-21T08:35+08:00","fxLink":"https://www.qweather.com/weather/guangzhou-101280101.html","daily":[{"fxDate":"2023-08-21","sunrise":"06:05","sunset":"18:57","moonrise":"09:54","moonset":"21:47","moonPhase":"峨眉月","moonPhaseIcon":"801","tempMax":"32","tempMin":"26","iconDay":"302","textDay":"雷阵雨","iconNight":"104","textNight":"阴","wind360Day":"0","windDirDay":"北风","windScaleDay":"微风","windSpeedDay":"3","wind360Night":"0","windDirNight":"北风","windScaleNight":"微风","windSpeedNight":"3","humidity":"74","precip":"2.5","pressure":"1004","vis":"25","cloud":"60","uvIndex":"8"},{"fxDate":"2023-08-22","sunrise":"06:06","sunset":"18:56","moonrise":"10:49","moonset":"22:21","moonPhase":"峨眉月","moonPhaseIcon":"801","tempMax":"33","tempMin":"27","iconDay":"104","textDay":"阴","iconNight":"104","textNight":"阴","wind360Day":"0","windDirDay":"北风","windScaleDay":"微风","windSpeedDay":"3","wind360Night":"0","windDirNight":"北风","windScaleNight":"微风","windSpeedNight":"3","humidity":"74","precip":"2.5","pressure":"1002","vis":"24","cloud":"60","uvIndex":"9"},{"fxDate":"2023-08-23","sunrise":"06:06","sunset":"18:55","moonrise":"11:46","moonset":"23:01","moonPhase":"峨眉月","moonPhaseIcon":"801","tempMax":"34","tempMin":"26","iconDay":"306","textDay":"中雨","iconNight":"302","textNight":"雷阵雨","wind360Day":"0","windDirDay":"北风","windScaleDay":"微风","windSpeedDay":"3","wind360Night":"0","windDirNight":"北风","windScaleNight":"微风","windSpeedNight":"3","humidity":"82","precip":"2.5","pressure":"1004","vis":"18","cloud":"60","uvIndex":"5"},{"fxDate":"2023-08-24","sunrise":"06:07","sunset":"18:54","moonrise":"12:47","moonset":"23:46","moonPhase":"上弦月","moonPhaseIcon":"802","tempMax":"34","tempMin":"26","iconDay":"302","textDay":"雷阵雨","iconNight":"302","textNight":"雷阵雨","wind360Day":"0","windDirDay":"北风","windScaleDay":"微风","windSpeedDay":"3","wind360Night":"0","windDirNight":"北风","windScaleNight":"微风","windSpeedNight":"3","humidity":"74","precip":"2.5","pressure":"1004","vis":"24","cloud":"60","uvIndex":"7"},{"fxDate":"2023-08-25","sunrise":"06:07","sunset":"18:54","moonrise":"13:51","moonset":"","moonPhase":"盈凸月","moonPhaseIcon":"803","tempMax":"33","tempMin":"26","iconDay":"302","textDay":"雷阵雨","iconNight":"302","textNight":"雷阵雨","wind360Day":"0","windDirDay":"北风","windScaleDay":"微风","windSpeedDay":"3","wind360Night":"0","windDirNight":"北风","windScaleNight":"微风","windSpeedNight":"3","humidity":"77","precip":"5.1","pressure":"1004","vis":"19","cloud":"62","uvIndex":"5"},{"fxDate":"2023-08-26","sunrise":"06:07","sunset":"18:53","moonrise":"14:55","moonset":"00:39","moonPhase":"盈凸月","moonPhaseIcon":"803","tempMax":"34","tempMin":"26","iconDay":"302","textDay":"雷阵雨","iconNight":"302","textNight":"雷阵雨","wind360Day":"135","windDirDay":"东南风","windScaleDay":"3-4","windSpeedDay":"16","wind360Night":"0","windDirNight":"北风","windScaleNight":"微风","windSpeedNight":"3","humidity":"77","precip":"5.1","pressure":"1004","vis":"25","cloud":"62","uvIndex":"5"},{"fxDate":"2023-08-27","sunrise":"06:08","sunset":"18:52","moonrise":"15:57","moonset":"01:38","moonPhase":"盈凸月","moonPhaseIcon":"803","tempMax":"34","tempMin":"26","iconDay":"302","textDay":"雷阵雨","iconNight":"302","textNight":"雷阵雨","wind360Day":"135","windDirDay":"东南风","windScaleDay":"3-4","windSpeedDay":"16","wind360Night":"135","windDirNight":"东南风","windScaleNight":"3-4","windSpeedNight":"16","humidity":"74","precip":"3.8","pressure":"1003","vis":"25","cloud":"72","uvIndex":"7"}],"refer":{"sources":["QWeather","NMC","ECMWF"],"license":["CC BY-SA 4.0"]}}